retracesoftware_functional.cpython-311-darwin.so
retracesoftware_functional_debug-0.1.18.dist-info/RECORD
retracesoftware_functional_debug-0.1.18.dist-info/WHEEL
retracesoftware_functional_debug-0.1.18.dist-info/METADATA
retracesoftware_functional_debug-0.1.18.data/purelib/retracesoftware/functional.py
